beautyspot/__init__.py
beautyspot/cachekey.py
beautyspot/cli.py
beautyspot/core.py
beautyspot/dashboard.py
beautyspot/db.py
beautyspot/limiter.py
beautyspot/serializer.py
beautyspot/storage.py
beautyspot/types.py
beautyspot-2.2.4.dist-info/WHEEL
beautyspot-2.2.4.dist-info/entry_points.txt
beautyspot-2.2.4.dist-info/METADATA
beautyspot-2.2.4.dist-info/RECORD
