Metadata-Version: 2.4
Name: beautyspot
Version: 2.2.4
Summary: Make your functions beautiful with beauty spots.
Author: Neel Bauman
Author-email: Neel Bauman <neel.bauman@example.com>
License-Expression: MIT
Requires-Dist: msgpack>=1.1.2
Requires-Dist: streamlit>=1.51.0
Requires-Dist: pandas>=2.3.3 ; extra == 'all'
Requires-Dist: streamlit>=1.51.0 ; extra == 'all'
Requires-Dist: watchdog>=6.0.0 ; extra == 'all'
Requires-Dist: boto3>=1.34.0 ; extra == 'all'
Requires-Dist: graphviz>=0.20.1 ; extra == 'all'
Requires-Dist: rich>=14.3.1 ; extra == 'all'
Requires-Dist: typer>=0.21.1 ; extra == 'all'
Requires-Dist: pandas>=2.3.3 ; extra == 'dashboard'
Requires-Dist: streamlit>=1.51.0 ; extra == 'dashboard'
Requires-Dist: watchdog>=6.0.0 ; extra == 'dashboard'
Requires-Dist: graphviz>=0.20.1 ; extra == 'dashboard'
Requires-Dist: rich>=14.3.1 ; extra == 'dashboard'
Requires-Dist: typer>=0.21.1 ; extra == 'dashboard'
Requires-Dist: boto3>=1.34.0 ; extra == 's3'
Requires-Python: >=3.10
Provides-Extra: all
Provides-Extra: dashboard
Provides-Extra: s3
